<?xml version="1.0" encoding="utf-8"?>
<Messages>
	<Message severity="INFO" prefix="[HLS 200-111]" key="HLS_111_966" tag="RUNTIME" content="Finished File checks and directory preparation: CPU user time: 0 seconds. CPU system time: 0 seconds. Elapsed time: 0 seconds; current allocated memory: 155.932 MB." resolution=""/>
	<Message severity="INFO" prefix="[HLS 200-10]" key="HLS_10_1312" tag="" content="Analyzing design file &apos;conv_bckwd/main.cpp&apos; ..." resolution=""/>
	<Message severity="INFO" prefix="[HLS 200-111]" key="HLS_111_966" tag="RUNTIME" content="Finished Source Code Analysis and Preprocessing: CPU user time: 3.4 seconds. CPU system time: 0.18 seconds. Elapsed time: 2.94 seconds; current allocated memory: 157.642 MB." resolution=""/>
	<Message severity="INFO" prefix="[HLS 200-777]" key="HLS 200-777" tag="" content="Using interface defaults for &apos;Vivado&apos; flow target." resolution=""/>
	<Message severity="WARNING" prefix="[HLS 214-205]" key="HLS 214-205" tag="" content="The INTERFACE pragma must have a max_widen_bitwidth setting that is both a power of 2 and in the range [0, 1024]. The current value of &apos;0&apos; will be ignored, in &apos;conv_bckwd(ap_fixed&lt;16, 9, (ap_q_mode)5, (ap_o_mode)3, 0&gt;*, ap_fixed&lt;16, 9, (ap_q_mode)5, (ap_o_mode)3, 0&gt;*, ap_fixed&lt;16, 9, (ap_q_mode)5, (ap_o_mode)3, 0&gt;*, ap_fixed&lt;16, 9, (ap_q_mode)5, (ap_o_mode)3, 0&gt;*, ap_fixed&lt;16, 9, (ap_q_mode)5, (ap_o_mode)3, 0&gt;*, ap_fixed&lt;16, 9, (ap_q_mode)5, (ap_o_mode)3, 0&gt;*, int, int, int, int, int, int)&apos; (conv_bckwd/main.cpp:3:0)" resolution=""/>
	<Message severity="WARNING" prefix="[HLS 214-205]" key="HLS 214-205" tag="" content="The INTERFACE pragma must have a max_widen_bitwidth setting that is both a power of 2 and in the range [0, 1024]. The current value of &apos;0&apos; will be ignored, in &apos;conv_bckwd(ap_fixed&lt;16, 9, (ap_q_mode)5, (ap_o_mode)3, 0&gt;*, ap_fixed&lt;16, 9, (ap_q_mode)5, (ap_o_mode)3, 0&gt;*, ap_fixed&lt;16, 9, (ap_q_mode)5, (ap_o_mode)3, 0&gt;*, ap_fixed&lt;16, 9, (ap_q_mode)5, (ap_o_mode)3, 0&gt;*, ap_fixed&lt;16, 9, (ap_q_mode)5, (ap_o_mode)3, 0&gt;*, ap_fixed&lt;16, 9, (ap_q_mode)5, (ap_o_mode)3, 0&gt;*, int, int, int, int, int, int)&apos; (conv_bckwd/main.cpp:3:0)" resolution=""/>
	<Message severity="WARNING" prefix="[HLS 214-205]" key="HLS 214-205" tag="" content="The INTERFACE pragma must have a max_widen_bitwidth setting that is both a power of 2 and in the range [0, 1024]. The current value of &apos;0&apos; will be ignored, in &apos;conv_bckwd(ap_fixed&lt;16, 9, (ap_q_mode)5, (ap_o_mode)3, 0&gt;*, ap_fixed&lt;16, 9, (ap_q_mode)5, (ap_o_mode)3, 0&gt;*, ap_fixed&lt;16, 9, (ap_q_mode)5, (ap_o_mode)3, 0&gt;*, ap_fixed&lt;16, 9, (ap_q_mode)5, (ap_o_mode)3, 0&gt;*, ap_fixed&lt;16, 9, (ap_q_mode)5, (ap_o_mode)3, 0&gt;*, ap_fixed&lt;16, 9, (ap_q_mode)5, (ap_o_mode)3, 0&gt;*, int, int, int, int, int, int)&apos; (conv_bckwd/main.cpp:3:0)" resolution=""/>
	<Message severity="WARNING" prefix="[HLS 214-205]" key="HLS 214-205" tag="" content="The INTERFACE pragma must have a max_widen_bitwidth setting that is both a power of 2 and in the range [0, 1024]. The current value of &apos;0&apos; will be ignored, in &apos;conv_bckwd(ap_fixed&lt;16, 9, (ap_q_mode)5, (ap_o_mode)3, 0&gt;*, ap_fixed&lt;16, 9, (ap_q_mode)5, (ap_o_mode)3, 0&gt;*, ap_fixed&lt;16, 9, (ap_q_mode)5, (ap_o_mode)3, 0&gt;*, ap_fixed&lt;16, 9, (ap_q_mode)5, (ap_o_mode)3, 0&gt;*, ap_fixed&lt;16, 9, (ap_q_mode)5, (ap_o_mode)3, 0&gt;*, ap_fixed&lt;16, 9, (ap_q_mode)5, (ap_o_mode)3, 0&gt;*, int, int, int, int, int, int)&apos; (conv_bckwd/main.cpp:3:0)" resolution=""/>
	<Message severity="WARNING" prefix="[HLS 214-205]" key="HLS 214-205" tag="" content="The INTERFACE pragma must have a max_widen_bitwidth setting that is both a power of 2 and in the range [0, 1024]. The current value of &apos;0&apos; will be ignored, in &apos;conv_bckwd(ap_fixed&lt;16, 9, (ap_q_mode)5, (ap_o_mode)3, 0&gt;*, ap_fixed&lt;16, 9, (ap_q_mode)5, (ap_o_mode)3, 0&gt;*, ap_fixed&lt;16, 9, (ap_q_mode)5, (ap_o_mode)3, 0&gt;*, ap_fixed&lt;16, 9, (ap_q_mode)5, (ap_o_mode)3, 0&gt;*, ap_fixed&lt;16, 9, (ap_q_mode)5, (ap_o_mode)3, 0&gt;*, ap_fixed&lt;16, 9, (ap_q_mode)5, (ap_o_mode)3, 0&gt;*, int, int, int, int, int, int)&apos; (conv_bckwd/main.cpp:3:0)" resolution=""/>
	<Message severity="WARNING" prefix="[HLS 214-205]" key="HLS 214-205" tag="" content="The INTERFACE pragma must have a max_widen_bitwidth setting that is both a power of 2 and in the range [0, 1024]. The current value of &apos;0&apos; will be ignored, in &apos;conv_bckwd(ap_fixed&lt;16, 9, (ap_q_mode)5, (ap_o_mode)3, 0&gt;*, ap_fixed&lt;16, 9, (ap_q_mode)5, (ap_o_mode)3, 0&gt;*, ap_fixed&lt;16, 9, (ap_q_mode)5, (ap_o_mode)3, 0&gt;*, ap_fixed&lt;16, 9, (ap_q_mode)5, (ap_o_mode)3, 0&gt;*, ap_fixed&lt;16, 9, (ap_q_mode)5, (ap_o_mode)3, 0&gt;*, ap_fixed&lt;16, 9, (ap_q_mode)5, (ap_o_mode)3, 0&gt;*, int, int, int, int, int, int)&apos; (conv_bckwd/main.cpp:3:0)" resolution=""/>
	<Message severity="INFO" prefix="[HLS 214-115]" key="HLS 214-115" tag="VITIS_INTERFACE" content="Multiple burst reads of variable length and bit width 16 in loop &apos;VITIS_LOOP_35_3&apos;(conv_bckwd/main.cpp:35:30) has been inferred on port &apos;gmem&apos; (conv_bckwd/main.cpp:35:30)" resolution=""/>
	<Message severity="INFO" prefix="[HLS 214-115]" key="HLS 214-115" tag="VITIS_INTERFACE" content="Multiple burst reads of variable length and bit width 16 in loop &apos;VITIS_LOOP_46_7&apos;(conv_bckwd/main.cpp:46:34) has been inferred on port &apos;gmem&apos; (conv_bckwd/main.cpp:46:34)" resolution=""/>
	<Message severity="INFO" prefix="[HLS 214-115]" key="HLS 214-115" tag="VITIS_INTERFACE" content="Multiple burst reads of variable length and bit width 16 in loop &apos;VITIS_LOOP_64_10&apos;(conv_bckwd/main.cpp:64:31) has been inferred on port &apos;gmem&apos; (conv_bckwd/main.cpp:64:31)" resolution=""/>
	<Message severity="INFO" prefix="[HLS 214-115]" key="HLS 214-115" tag="VITIS_INTERFACE" content="Multiple burst reads of variable length and bit width 16 in loop &apos;VITIS_LOOP_81_14&apos;(conv_bckwd/main.cpp:81:35) has been inferred on port &apos;gmem&apos; (conv_bckwd/main.cpp:81:35)" resolution=""/>
	<Message severity="INFO" prefix="[HLS 214-115]" key="HLS 214-115" tag="VITIS_INTERFACE" content="Multiple burst reads of variable length and bit width 16 in loop &apos;VITIS_LOOP_90_17&apos;(conv_bckwd/main.cpp:90:31) has been inferred on port &apos;gmem&apos; (conv_bckwd/main.cpp:90:31)" resolution=""/>
	<Message severity="INFO" prefix="[HLS 214-115]" key="HLS 214-115" tag="VITIS_INTERFACE" content="Multiple burst writes of variable length and bit width 16 in loop &apos;VITIS_LOOP_97_18&apos;(conv_bckwd/main.cpp:97:23) has been inferred on port &apos;gmem&apos; (conv_bckwd/main.cpp:97:23)" resolution=""/>
	<Message severity="INFO" prefix="[HLS 214-115]" key="HLS 214-115" tag="VITIS_INTERFACE" content="Multiple burst writes of variable length and bit width 16 in loop &apos;VITIS_LOOP_124_28&apos;(conv_bckwd/main.cpp:124:36) has been inferred on port &apos;gmem&apos; (conv_bckwd/main.cpp:124:36)" resolution=""/>
	<Message severity="INFO" prefix="[HLS 214-115]" key="HLS 214-115" tag="VITIS_INTERFACE" content="Multiple burst writes of variable length and bit width 16 in loop &apos;VITIS_LOOP_133_31&apos;(conv_bckwd/main.cpp:133:32) has been inferred on port &apos;gmem&apos; (conv_bckwd/main.cpp:133:32)" resolution=""/>
	<Message severity="INFO" prefix="[HLS 214-115]" key="HLS 214-115" tag="VITIS_INTERFACE" content="Multiple burst writes of variable length and bit width 16 in loop &apos;VITIS_LOOP_140_32&apos;(conv_bckwd/main.cpp:140:24) has been inferred on port &apos;gmem&apos; (conv_bckwd/main.cpp:140:24)" resolution=""/>
	<Message severity="INFO" prefix="[HLS 214-131]" key="HLS 214-131" tag="" content="Inlining function &apos;_llvm.fpga.pack.none.i16.s_struct.ap_fixeds&apos; into &apos;conv_bckwd(ap_fixed&lt;16, 9, (ap_q_mode)5, (ap_o_mode)3, 0&gt;*, ap_fixed&lt;16, 9, (ap_q_mode)5, (ap_o_mode)3, 0&gt;*, ap_fixed&lt;16, 9, (ap_q_mode)5, (ap_o_mode)3, 0&gt;*, ap_fixed&lt;16, 9, (ap_q_mode)5, (ap_o_mode)3, 0&gt;*, ap_fixed&lt;16, 9, (ap_q_mode)5, (ap_o_mode)3, 0&gt;*, ap_fixed&lt;16, 9, (ap_q_mode)5, (ap_o_mode)3, 0&gt;*, int, int, int, int, int, int)&apos; (conv_bckwd/main.cpp:98:15)" resolution=""/>
	<Message severity="INFO" prefix="[HLS 214-131]" key="HLS 214-131" tag="" content="Inlining function &apos;_llvm.fpga.pack.none.i16.s_struct.ap_fixeds&apos; into &apos;conv_bckwd(ap_fixed&lt;16, 9, (ap_q_mode)5, (ap_o_mode)3, 0&gt;*, ap_fixed&lt;16, 9, (ap_q_mode)5, (ap_o_mode)3, 0&gt;*, ap_fixed&lt;16, 9, (ap_q_mode)5, (ap_o_mode)3, 0&gt;*, ap_fixed&lt;16, 9, (ap_q_mode)5, (ap_o_mode)3, 0&gt;*, ap_fixed&lt;16, 9, (ap_q_mode)5, (ap_o_mode)3, 0&gt;*, ap_fixed&lt;16, 9, (ap_q_mode)5, (ap_o_mode)3, 0&gt;*, int, int, int, int, int, int)&apos; (conv_bckwd/main.cpp:141:15)" resolution=""/>
	<Message severity="INFO" prefix="[HLS 214-131]" key="HLS 214-131" tag="" content="Inlining function &apos;_llvm.fpga.pack.none.i16.s_struct.ap_fixeds&apos; into &apos;conv_bckwd(ap_fixed&lt;16, 9, (ap_q_mode)5, (ap_o_mode)3, 0&gt;*, ap_fixed&lt;16, 9, (ap_q_mode)5, (ap_o_mode)3, 0&gt;*, ap_fixed&lt;16, 9, (ap_q_mode)5, (ap_o_mode)3, 0&gt;*, ap_fixed&lt;16, 9, (ap_q_mode)5, (ap_o_mode)3, 0&gt;*, ap_fixed&lt;16, 9, (ap_q_mode)5, (ap_o_mode)3, 0&gt;*, ap_fixed&lt;16, 9, (ap_q_mode)5, (ap_o_mode)3, 0&gt;*, int, int, int, int, int, int)&apos; (conv_bckwd/main.cpp:134:33)" resolution=""/>
	<Message severity="INFO" prefix="[HLS 214-131]" key="HLS 214-131" tag="" content="Inlining function &apos;_llvm.fpga.pack.none.i16.s_struct.ap_fixeds&apos; into &apos;conv_bckwd(ap_fixed&lt;16, 9, (ap_q_mode)5, (ap_o_mode)3, 0&gt;*, ap_fixed&lt;16, 9, (ap_q_mode)5, (ap_o_mode)3, 0&gt;*, ap_fixed&lt;16, 9, (ap_q_mode)5, (ap_o_mode)3, 0&gt;*, ap_fixed&lt;16, 9, (ap_q_mode)5, (ap_o_mode)3, 0&gt;*, ap_fixed&lt;16, 9, (ap_q_mode)5, (ap_o_mode)3, 0&gt;*, ap_fixed&lt;16, 9, (ap_q_mode)5, (ap_o_mode)3, 0&gt;*, int, int, int, int, int, int)&apos; (conv_bckwd/main.cpp:125:50)" resolution=""/>
	<Message severity="INFO" prefix="[HLS 200-111]" key="HLS_111_966" tag="RUNTIME" content="Finished Compiling Optimization and Transform: CPU user time: 3.06 seconds. CPU system time: 0.2 seconds. Elapsed time: 3.26 seconds; current allocated memory: 160.134 MB." resolution=""/>
	<Message severity="INFO" prefix="[HLS 200-111]" key="HLS_111_966" tag="RUNTIME" content="Finished Checking Pragmas: CPU user time: 0.01 seconds. CPU system time: 0 seconds. Elapsed time: 0 seconds; current allocated memory: 160.136 MB." resolution=""/>
	<Message severity="INFO" prefix="[HLS 200-10]" key="HLS_10_1467" tag="" content="Starting code transformations ..." resolution=""/>
	<Message severity="INFO" prefix="[HLS 200-111]" key="HLS_111_966" tag="RUNTIME" content="Finished Standard Transforms: CPU user time: 0.07 seconds. CPU system time: 0.01 seconds. Elapsed time: 0.08 seconds; current allocated memory: 165.882 MB." resolution=""/>
	<Message severity="INFO" prefix="[HLS 200-10]" key="HLS_10_1472" tag="" content="Checking synthesizability ..." resolution=""/>
	<Message severity="INFO" prefix="[HLS 200-111]" key="HLS_111_966" tag="RUNTIME" content="Finished Checking Synthesizability: CPU user time: 0.13 seconds. CPU system time: 0 seconds. Elapsed time: 0.12 seconds; current allocated memory: 169.800 MB." resolution=""/>
	<Message severity="INFO" prefix="[XFORM 203-510]" key="XFORM_AUTO_PIPELINE_STATUS_244" tag="" content="Pipelining loop &apos;VITIS_LOOP_35_3&apos; (conv_bckwd/main.cpp:35) in function &apos;conv_bckwd&apos; automatically." resolution=""/>
	<Message severity="INFO" prefix="[XFORM 203-510]" key="XFORM_AUTO_PIPELINE_STATUS_244" tag="" content="Pipelining loop &apos;VITIS_LOOP_46_7&apos; (conv_bckwd/main.cpp:46) in function &apos;conv_bckwd&apos; automatically." resolution=""/>
	<Message severity="INFO" prefix="[XFORM 203-510]" key="XFORM_AUTO_PIPELINE_STATUS_244" tag="" content="Pipelining loop &apos;VITIS_LOOP_64_10&apos; (conv_bckwd/main.cpp:64) in function &apos;conv_bckwd&apos; automatically." resolution=""/>
	<Message severity="INFO" prefix="[XFORM 203-510]" key="XFORM_AUTO_PIPELINE_STATUS_244" tag="" content="Pipelining loop &apos;VITIS_LOOP_81_14&apos; (conv_bckwd/main.cpp:81) in function &apos;conv_bckwd&apos; automatically." resolution=""/>
	<Message severity="INFO" prefix="[XFORM 203-510]" key="XFORM_AUTO_PIPELINE_STATUS_244" tag="" content="Pipelining loop &apos;VITIS_LOOP_90_17&apos; (conv_bckwd/main.cpp:90) in function &apos;conv_bckwd&apos; automatically." resolution=""/>
	<Message severity="INFO" prefix="[XFORM 203-510]" key="XFORM_AUTO_PIPELINE_STATUS_244" tag="" content="Pipelining loop &apos;VITIS_LOOP_97_18&apos; (conv_bckwd/main.cpp:97) in function &apos;conv_bckwd&apos; automatically." resolution=""/>
	<Message severity="INFO" prefix="[XFORM 203-510]" key="XFORM_AUTO_PIPELINE_STATUS_244" tag="" content="Pipelining loop &apos;VITIS_LOOP_108_24&apos; (conv_bckwd/main.cpp:108) in function &apos;conv_bckwd&apos; automatically." resolution=""/>
	<Message severity="INFO" prefix="[XFORM 203-510]" key="XFORM_AUTO_PIPELINE_STATUS_244" tag="" content="Pipelining loop &apos;VITIS_LOOP_124_28&apos; (conv_bckwd/main.cpp:124) in function &apos;conv_bckwd&apos; automatically." resolution=""/>
	<Message severity="INFO" prefix="[XFORM 203-510]" key="XFORM_AUTO_PIPELINE_STATUS_244" tag="" content="Pipelining loop &apos;VITIS_LOOP_133_31&apos; (conv_bckwd/main.cpp:133) in function &apos;conv_bckwd&apos; automatically." resolution=""/>
	<Message severity="INFO" prefix="[XFORM 203-510]" key="XFORM_AUTO_PIPELINE_STATUS_244" tag="" content="Pipelining loop &apos;VITIS_LOOP_140_32&apos; (conv_bckwd/main.cpp:140) in function &apos;conv_bckwd&apos; automatically." resolution=""/>
	<Message severity="INFO" prefix="[HLS 200-111]" key="HLS_111_966" tag="RUNTIME" content="Finished Loop, function and other optimizations: CPU user time: 0.51 seconds. CPU system time: 0.01 seconds. Elapsed time: 0.53 seconds; current allocated memory: 197.481 MB." resolution=""/>
	<Message severity="WARNING" prefix="[HLS 200-960]" key="HLS 200-960" tag="LOOP,VITIS_LATENCY" content="Cannot flatten loop &apos;VITIS_LOOP_34_2&apos; (conv_bckwd/main.cpp:34:34) in function &apos;conv_bckwd&apos; the outer loop is not a perfect loop because there is nontrivial logic before entering the inner loop." resolution="http://www.xilinx.com/cgi-bin/docs/rdoc?v=2020.2;t=hls+guidance;d=200-960.html"/>
	<Message severity="INFO" prefix="[XFORM 203-541]" key="XFORM_LOOPFLAT_STATUS_218" tag="" content="Flattening a loop nest &apos;VITIS_LOOP_33_1&apos; (conv_bckwd/main.cpp:33:30) in function &apos;conv_bckwd&apos;." resolution=""/>
	<Message severity="WARNING" prefix="[HLS 200-960]" key="HLS 200-960" tag="LOOP,VITIS_LATENCY" content="Cannot flatten loop &apos;VITIS_LOOP_45_6&apos; (conv_bckwd/main.cpp:45:38) in function &apos;conv_bckwd&apos; the outer loop is not a perfect loop because there is nontrivial logic before entering the inner loop." resolution="http://www.xilinx.com/cgi-bin/docs/rdoc?v=2020.2;t=hls+guidance;d=200-960.html"/>
	<Message severity="INFO" prefix="[XFORM 203-541]" key="XFORM_LOOPFLAT_STATUS_218" tag="" content="Flattening a loop nest &apos;VITIS_LOOP_44_5&apos; (conv_bckwd/main.cpp:44:34) in function &apos;conv_bckwd&apos;." resolution=""/>
	<Message severity="INFO" prefix="[XFORM 203-541]" key="XFORM_LOOPFLAT_STATUS_218" tag="" content="Flattening a loop nest &apos;VITIS_LOOP_43_4&apos; (conv_bckwd/main.cpp:43:30) in function &apos;conv_bckwd&apos;." resolution=""/>
	<Message severity="WARNING" prefix="[HLS 200-960]" key="HLS 200-960" tag="LOOP,VITIS_LATENCY" content="Cannot flatten loop &apos;VITIS_LOOP_63_9&apos; (conv_bckwd/main.cpp:63:34) in function &apos;conv_bckwd&apos; the outer loop is not a perfect loop because there is nontrivial logic before entering the inner loop." resolution="http://www.xilinx.com/cgi-bin/docs/rdoc?v=2020.2;t=hls+guidance;d=200-960.html"/>
	<Message severity="INFO" prefix="[XFORM 203-541]" key="XFORM_LOOPFLAT_STATUS_218" tag="" content="Flattening a loop nest &apos;VITIS_LOOP_62_8&apos; (conv_bckwd/main.cpp:62:30) in function &apos;conv_bckwd&apos;." resolution=""/>
	<Message severity="WARNING" prefix="[HLS 200-960]" key="HLS 200-960" tag="LOOP,VITIS_LATENCY" content="Cannot flatten loop &apos;VITIS_LOOP_80_13&apos; (conv_bckwd/main.cpp:80:39) in function &apos;conv_bckwd&apos; the outer loop is not a perfect loop because there is nontrivial logic before entering the inner loop." resolution="http://www.xilinx.com/cgi-bin/docs/rdoc?v=2020.2;t=hls+guidance;d=200-960.html"/>
	<Message severity="INFO" prefix="[XFORM 203-541]" key="XFORM_LOOPFLAT_STATUS_218" tag="" content="Flattening a loop nest &apos;VITIS_LOOP_79_12&apos; (conv_bckwd/main.cpp:79:35) in function &apos;conv_bckwd&apos;." resolution=""/>
	<Message severity="INFO" prefix="[XFORM 203-541]" key="XFORM_LOOPFLAT_STATUS_218" tag="" content="Flattening a loop nest &apos;VITIS_LOOP_78_11&apos; (conv_bckwd/main.cpp:78:31) in function &apos;conv_bckwd&apos;." resolution=""/>
	<Message severity="WARNING" prefix="[HLS 200-960]" key="HLS 200-960" tag="LOOP,VITIS_LATENCY" content="Cannot flatten loop &apos;VITIS_LOOP_89_16&apos; (conv_bckwd/main.cpp:89:35) in function &apos;conv_bckwd&apos; the outer loop is not a perfect loop because there is nontrivial logic before entering the inner loop." resolution="http://www.xilinx.com/cgi-bin/docs/rdoc?v=2020.2;t=hls+guidance;d=200-960.html"/>
	<Message severity="INFO" prefix="[XFORM 203-541]" key="XFORM_LOOPFLAT_STATUS_218" tag="" content="Flattening a loop nest &apos;VITIS_LOOP_88_15&apos; (conv_bckwd/main.cpp:88:31) in function &apos;conv_bckwd&apos;." resolution=""/>
	<Message severity="INFO" prefix="[XFORM 203-541]" key="XFORM_LOOPFLAT_STATUS_218" tag="" content="Flattening a loop nest &apos;VITIS_LOOP_107_23&apos; (conv_bckwd/main.cpp:107:48) in function &apos;conv_bckwd&apos;." resolution=""/>
	<Message severity="INFO" prefix="[XFORM 203-541]" key="XFORM_LOOPFLAT_STATUS_218" tag="" content="Flattening a loop nest &apos;VITIS_LOOP_106_22&apos; (conv_bckwd/main.cpp:106:44) in function &apos;conv_bckwd&apos;." resolution=""/>
	<Message severity="WARNING" prefix="[HLS 200-960]" key="HLS 200-960" tag="LOOP,VITIS_LATENCY" content="Cannot flatten loop &apos;VITIS_LOOP_105_21&apos; (conv_bckwd/main.cpp:105:40) in function &apos;conv_bckwd&apos; the outer loop is not a perfect loop." resolution="http://www.xilinx.com/cgi-bin/docs/rdoc?v=2020.2;t=hls+guidance;d=200-960.html"/>
	<Message severity="WARNING" prefix="[HLS 200-960]" key="HLS 200-960" tag="LOOP,VITIS_LATENCY" content="Cannot flatten loop &apos;VITIS_LOOP_104_20&apos; (conv_bckwd/main.cpp:104:36) in function &apos;conv_bckwd&apos; the outer loop is not a perfect loop because there is nontrivial logic before entering the inner loop." resolution="http://www.xilinx.com/cgi-bin/docs/rdoc?v=2020.2;t=hls+guidance;d=200-960.html"/>
	<Message severity="WARNING" prefix="[HLS 200-960]" key="HLS 200-960" tag="LOOP,VITIS_LATENCY" content="Cannot flatten loop &apos;VITIS_LOOP_103_19&apos; (conv_bckwd/main.cpp:103:32) in function &apos;conv_bckwd&apos; the outer loop is not a perfect loop because there is nontrivial logic before entering the inner loop." resolution="http://www.xilinx.com/cgi-bin/docs/rdoc?v=2020.2;t=hls+guidance;d=200-960.html"/>
	<Message severity="WARNING" prefix="[HLS 200-960]" key="HLS 200-960" tag="LOOP,VITIS_LATENCY" content="Cannot flatten loop &apos;VITIS_LOOP_123_27&apos; (conv_bckwd/main.cpp:123:40) in function &apos;conv_bckwd&apos; the outer loop is not a perfect loop because there is nontrivial logic before entering the inner loop." resolution="http://www.xilinx.com/cgi-bin/docs/rdoc?v=2020.2;t=hls+guidance;d=200-960.html"/>
	<Message severity="INFO" prefix="[XFORM 203-541]" key="XFORM_LOOPFLAT_STATUS_218" tag="" content="Flattening a loop nest &apos;VITIS_LOOP_122_26&apos; (conv_bckwd/main.cpp:122:36) in function &apos;conv_bckwd&apos;." resolution=""/>
	<Message severity="INFO" prefix="[XFORM 203-541]" key="XFORM_LOOPFLAT_STATUS_218" tag="" content="Flattening a loop nest &apos;VITIS_LOOP_121_25&apos; (conv_bckwd/main.cpp:121:32) in function &apos;conv_bckwd&apos;." resolution=""/>
	<Message severity="WARNING" prefix="[HLS 200-960]" key="HLS 200-960" tag="LOOP,VITIS_LATENCY" content="Cannot flatten loop &apos;VITIS_LOOP_132_30&apos; (conv_bckwd/main.cpp:132:36) in function &apos;conv_bckwd&apos; the outer loop is not a perfect loop because there is nontrivial logic before entering the inner loop." resolution="http://www.xilinx.com/cgi-bin/docs/rdoc?v=2020.2;t=hls+guidance;d=200-960.html"/>
	<Message severity="INFO" prefix="[XFORM 203-541]" key="XFORM_LOOPFLAT_STATUS_218" tag="" content="Flattening a loop nest &apos;VITIS_LOOP_131_29&apos; (conv_bckwd/main.cpp:131:32) in function &apos;conv_bckwd&apos;." resolution=""/>
	<Message severity="INFO" prefix="[HLS 200-472]" key="HLS 200-472" tag="" content="Inferring partial write operation for &apos;xbuf.V&apos; (conv_bckwd/main.cpp:36:31)" resolution=""/>
	<Message severity="INFO" prefix="[HLS 200-472]" key="HLS 200-472" tag="" content="Inferring partial write operation for &apos;wbuf.V&apos; (conv_bckwd/main.cpp:47:38)" resolution=""/>
	<Message severity="INFO" prefix="[HLS 200-472]" key="HLS 200-472" tag="" content="Inferring partial write operation for &apos;dybuf.V&apos; (conv_bckwd/main.cpp:65:32)" resolution=""/>
	<Message severity="INFO" prefix="[HLS 200-472]" key="HLS 200-472" tag="" content="Inferring partial write operation for &apos;dwbuf.V&apos; (conv_bckwd/main.cpp:82:39)" resolution=""/>
	<Message severity="INFO" prefix="[HLS 200-472]" key="HLS 200-472" tag="" content="Inferring partial write operation for &apos;dxbuf.V&apos; (conv_bckwd/main.cpp:91:32)" resolution=""/>
	<Message severity="INFO" prefix="[HLS 200-472]" key="HLS 200-472" tag="" content="Inferring partial write operation for &apos;dwbuf.V&apos;" resolution=""/>
	<Message severity="INFO" prefix="[HLS 200-472]" key="HLS 200-472" tag="" content="Inferring partial write operation for &apos;dbbuf.V&apos;" resolution=""/>
	<Message severity="INFO" prefix="[HLS 200-111]" key="HLS_111_966" tag="RUNTIME" content="Finished Architecture Synthesis: CPU user time: 0.48 seconds. CPU system time: 0 seconds. Elapsed time: 0.5 seconds; current allocated memory: 197.384 MB." resolution=""/>
	<Message severity="INFO" prefix="[HLS 200-10]" key="HLS_10_1317" tag="" content="Starting hardware synthesis ..." resolution=""/>
	<Message severity="INFO" prefix="[HLS 200-10]" key="HLS_10_1385" tag="" content="Synthesizing &apos;conv_bckwd&apos; ..." resolution=""/>
	<Message severity="WARNING" prefix="[SYN 201-107]" key="SYN_PORT_NAME_ILLEGAL_593" tag="" content="Renaming port name &apos;conv_bckwd/W&apos; to &apos;conv_bckwd/W_r&apos; to avoid the conflict with HDL keywords or other object names." resolution=""/>
	<Message severity="INFO" prefix="[HLS 200-10]" key="HLS_10_1477" tag="" content="----------------------------------------------------------------" resolution=""/>
	<Message severity="INFO" prefix="[HLS 200-42]" key="HLS_42_1438" tag="" content="-- Implementing module &apos;conv_bckwd&apos;" resolution=""/>
	<Message severity="INFO" prefix="[HLS 200-10]" key="HLS_10_1478" tag="" content="----------------------------------------------------------------" resolution=""/>
	<Message severity="INFO" prefix="[SCHED 204-11]" key="SCHED_SCHED_STATUS_597" tag="" content="Starting scheduling ..." resolution=""/>
	<Message severity="INFO" prefix="[HLS 200-486]" key="HLS 200-486" tag="" content="Changing DSP48 latency (root=add_ln36) to 3 in order to utilize available DSP registers." resolution=""/>
	<Message severity="INFO" prefix="[HLS 200-486]" key="HLS 200-486" tag="" content="Changing DSP48 latency (root=add_ln65) to 3 in order to utilize available DSP registers." resolution=""/>
	<Message severity="INFO" prefix="[HLS 200-486]" key="HLS 200-486" tag="" content="Changing DSP48 latency (root=add_ln91) to 3 in order to utilize available DSP registers." resolution=""/>
	<Message severity="INFO" prefix="[HLS 200-486]" key="HLS 200-486" tag="" content="Changing DSP48 latency (root=empty_85) to 3 in order to utilize available DSP registers." resolution=""/>
	<Message severity="INFO" prefix="[HLS 200-486]" key="HLS 200-486" tag="" content="Changing DSP48 latency (root=mul_ln1192_1) to 3 in order to utilize available DSP registers." resolution=""/>
	<Message severity="INFO" prefix="[HLS 200-486]" key="HLS 200-486" tag="" content="Changing DSP48 latency (root=mul_ln1192) to 3 in order to utilize available DSP registers." resolution=""/>
	<Message severity="INFO" prefix="[HLS 200-486]" key="HLS 200-486" tag="" content="Changing DSP48 latency (root=mul_ln1118_1) to 3 in order to utilize available DSP registers." resolution=""/>
	<Message severity="INFO" prefix="[HLS 200-486]" key="HLS 200-486" tag="" content="Changing DSP48 latency (root=mul_ln1118) to 3 in order to utilize available DSP registers." resolution=""/>
	<Message severity="INFO" prefix="[HLS 200-486]" key="HLS 200-486" tag="" content="Changing DSP48 latency (root=add_ln134) to 3 in order to utilize available DSP registers." resolution=""/>
	<Message severity="INFO" prefix="[SCHED 204-61]" key="SCHED_PIPELINING_STATUS_41" tag="" content="Pipelining loop &apos;VITIS_LOOP_35_3&apos;." resolution=""/>
	<Message severity="INFO" prefix="[HLS 200-1470]" key="HLS 200-1470" tag="SCHEDULE,VITIS_THROUGHPUT" content="Pipelining result : Target II = 1, Final II = 1, Depth = 3, loop &apos;VITIS_LOOP_35_3&apos;" resolution=""/>
	<Message severity="INFO" prefix="[SCHED 204-61]" key="SCHED_PIPELINING_STATUS_41" tag="" content="Pipelining loop &apos;VITIS_LOOP_46_7&apos;." resolution=""/>
	<Message severity="INFO" prefix="[HLS 200-1470]" key="HLS 200-1470" tag="SCHEDULE,VITIS_THROUGHPUT" content="Pipelining result : Target II = 1, Final II = 1, Depth = 3, loop &apos;VITIS_LOOP_46_7&apos;" resolution=""/>
	<Message severity="INFO" prefix="[SCHED 204-61]" key="SCHED_PIPELINING_STATUS_41" tag="" content="Pipelining loop &apos;VITIS_LOOP_64_10&apos;." resolution=""/>
	<Message severity="INFO" prefix="[HLS 200-1470]" key="HLS 200-1470" tag="SCHEDULE,VITIS_THROUGHPUT" content="Pipelining result : Target II = 1, Final II = 1, Depth = 3, loop &apos;VITIS_LOOP_64_10&apos;" resolution=""/>
	<Message severity="INFO" prefix="[SCHED 204-61]" key="SCHED_PIPELINING_STATUS_41" tag="" content="Pipelining loop &apos;VITIS_LOOP_81_14&apos;." resolution=""/>
	<Message severity="INFO" prefix="[HLS 200-1470]" key="HLS 200-1470" tag="SCHEDULE,VITIS_THROUGHPUT" content="Pipelining result : Target II = 1, Final II = 1, Depth = 3, loop &apos;VITIS_LOOP_81_14&apos;" resolution=""/>
	<Message severity="INFO" prefix="[SCHED 204-61]" key="SCHED_PIPELINING_STATUS_41" tag="" content="Pipelining loop &apos;VITIS_LOOP_90_17&apos;." resolution=""/>
	<Message severity="INFO" prefix="[HLS 200-1470]" key="HLS 200-1470" tag="SCHEDULE,VITIS_THROUGHPUT" content="Pipelining result : Target II = 1, Final II = 1, Depth = 3, loop &apos;VITIS_LOOP_90_17&apos;" resolution=""/>
	<Message severity="INFO" prefix="[SCHED 204-61]" key="SCHED_PIPELINING_STATUS_41" tag="" content="Pipelining loop &apos;VITIS_LOOP_97_18&apos;." resolution=""/>
	<Message severity="INFO" prefix="[HLS 200-1470]" key="HLS 200-1470" tag="SCHEDULE,VITIS_THROUGHPUT" content="Pipelining result : Target II = 1, Final II = 1, Depth = 3, loop &apos;VITIS_LOOP_97_18&apos;" resolution=""/>
	<Message severity="INFO" prefix="[SCHED 204-61]" key="SCHED_PIPELINING_STATUS_41" tag="" content="Pipelining loop &apos;VITIS_LOOP_106_22_VITIS_LOOP_107_23_VITIS_LOOP_108_24&apos;." resolution=""/>
	<Message severity="WARNING" prefix="[HLS 200-880]" key="HLS 200-880" tag="LOOP,SCHEDULE,VITIS_THROUGHPUT" content="The II Violation in module &apos;conv_bckwd&apos; (loop &apos;VITIS_LOOP_106_22_VITIS_LOOP_107_23_VITIS_LOOP_108_24&apos;): Unable to enforce a carried dependence constraint (II = 1, distance = 2, offset = 1) between &apos;store&apos; operation (&apos;dxbuf_V_addr_2_write_ln708&apos;) of variable &apos;trunc_ln708_1&apos; on array &apos;dxbuf.V&apos;, conv_bckwd/main.cpp:73 and &apos;load&apos; operation (&apos;dxbuf_V_load_1&apos;) on array &apos;dxbuf.V&apos;, conv_bckwd/main.cpp:73." resolution="http://www.xilinx.com/cgi-bin/docs/rdoc?v=2020.2;t=hls+guidance;d=200-880.html"/>
	<Message severity="INFO" prefix="[HLS 200-1470]" key="HLS 200-1470" tag="SCHEDULE,VITIS_THROUGHPUT" content="Pipelining result : Target II = 1, Final II = 2, Depth = 12, loop &apos;VITIS_LOOP_106_22_VITIS_LOOP_107_23_VITIS_LOOP_108_24&apos;" resolution=""/>
	<Message severity="INFO" prefix="[SCHED 204-61]" key="SCHED_PIPELINING_STATUS_41" tag="" content="Pipelining loop &apos;VITIS_LOOP_124_28&apos;." resolution=""/>
	<Message severity="INFO" prefix="[HLS 200-1470]" key="HLS 200-1470" tag="SCHEDULE,VITIS_THROUGHPUT" content="Pipelining result : Target II = 1, Final II = 1, Depth = 3, loop &apos;VITIS_LOOP_124_28&apos;" resolution=""/>
	<Message severity="INFO" prefix="[SCHED 204-61]" key="SCHED_PIPELINING_STATUS_41" tag="" content="Pipelining loop &apos;VITIS_LOOP_133_31&apos;." resolution=""/>
	<Message severity="INFO" prefix="[HLS 200-1470]" key="HLS 200-1470" tag="SCHEDULE,VITIS_THROUGHPUT" content="Pipelining result : Target II = 1, Final II = 1, Depth = 3, loop &apos;VITIS_LOOP_133_31&apos;" resolution=""/>
	<Message severity="INFO" prefix="[SCHED 204-61]" key="SCHED_PIPELINING_STATUS_41" tag="" content="Pipelining loop &apos;VITIS_LOOP_140_32&apos;." resolution=""/>
	<Message severity="INFO" prefix="[HLS 200-1470]" key="HLS 200-1470" tag="SCHEDULE,VITIS_THROUGHPUT" content="Pipelining result : Target II = 1, Final II = 1, Depth = 3, loop &apos;VITIS_LOOP_140_32&apos;" resolution=""/>
	<Message severity="INFO" prefix="[SCHED 204-11]" key="SCHED_SCHED_STATUS_596" tag="" content="Finished scheduling." resolution=""/>
	<Message severity="INFO" prefix="[HLS 200-111]" key="HLS_111_966" tag="RUNTIME" content="Finished Scheduling: CPU user time: 0.69 seconds. CPU system time: 0.01 seconds. Elapsed time: 0.71 seconds; current allocated memory: 200.071 MB." resolution=""/>
	<Message severity="INFO" prefix="[BIND 205-100]" key="BIND_100_926" tag="" content="Starting micro-architecture generation ..." resolution=""/>
	<Message severity="INFO" prefix="[BIND 205-101]" key="BIND_101_698" tag="" content="Performing variable lifetime analysis." resolution=""/>
	<Message severity="INFO" prefix="[BIND 205-101]" key="BIND_101_697" tag="" content="Exploring resource sharing." resolution=""/>
	<Message severity="INFO" prefix="[BIND 205-101]" key="BIND_101_693" tag="" content="Binding ..." resolution=""/>
	<Message severity="INFO" prefix="[BIND 205-100]" key="BIND_100_925" tag="" content="Finished micro-architecture generation." resolution=""/>
	<Message severity="INFO" prefix="[HLS 200-111]" key="HLS_111_966" tag="RUNTIME" content="Finished Binding: CPU user time: 0.88 seconds. CPU system time: 0.02 seconds. Elapsed time: 0.91 seconds; current allocated memory: 203.555 MB." resolution=""/>
	<Message severity="INFO" prefix="[HLS 200-10]" key="HLS_10_1483" tag="" content="----------------------------------------------------------------" resolution=""/>
	<Message severity="INFO" prefix="[HLS 200-10]" key="HLS_10_1484" tag="" content="-- Generating RTL for module &apos;conv_bckwd&apos;" resolution=""/>
	<Message severity="INFO" prefix="[HLS 200-10]" key="HLS_10_1485" tag="" content="----------------------------------------------------------------" resolution=""/>
	<Message severity="WARNING" prefix="[RTGEN 206-101]" key="RTGEN_101_918" tag="" content="Design contains AXI ports. Reset is fixed to synchronous and active low." resolution=""/>
	<Message severity="INFO" prefix="[RTGEN 206-500]" key="PREPROC_IO_COMP_CONFLICT_1950" tag="" content="Setting interface mode on port &apos;conv_bckwd/gmem&apos; to &apos;m_axi&apos;." resolution=""/>
	<Message severity="INFO" prefix="[RTGEN 206-500]" key="PREPROC_IO_COMP_CONFLICT_1950" tag="" content="Setting interface mode on port &apos;conv_bckwd/x&apos; to &apos;s_axilite &amp; ap_none&apos;." resolution=""/>
	<Message severity="INFO" prefix="[RTGEN 206-500]" key="PREPROC_IO_COMP_CONFLICT_1950" tag="" content="Setting interface mode on port &apos;conv_bckwd/w&apos; to &apos;s_axilite &amp; ap_none&apos;." resolution=""/>
	<Message severity="INFO" prefix="[RTGEN 206-500]" key="PREPROC_IO_COMP_CONFLICT_1950" tag="" content="Setting interface mode on port &apos;conv_bckwd/dx&apos; to &apos;s_axilite &amp; ap_none&apos;." resolution=""/>
	<Message severity="INFO" prefix="[RTGEN 206-500]" key="PREPROC_IO_COMP_CONFLICT_1950" tag="" content="Setting interface mode on port &apos;conv_bckwd/dw&apos; to &apos;s_axilite &amp; ap_none&apos;." resolution=""/>
	<Message severity="INFO" prefix="[RTGEN 206-500]" key="PREPROC_IO_COMP_CONFLICT_1950" tag="" content="Setting interface mode on port &apos;conv_bckwd/db&apos; to &apos;s_axilite &amp; ap_none&apos;." resolution=""/>
	<Message severity="INFO" prefix="[RTGEN 206-500]" key="PREPROC_IO_COMP_CONFLICT_1950" tag="" content="Setting interface mode on port &apos;conv_bckwd/dy&apos; to &apos;s_axilite &amp; ap_none&apos;." resolution=""/>
	<Message severity="INFO" prefix="[RTGEN 206-500]" key="PREPROC_IO_COMP_CONFLICT_1950" tag="" content="Setting interface mode on port &apos;conv_bckwd/F&apos; to &apos;s_axilite &amp; ap_none&apos;." resolution=""/>
	<Message severity="INFO" prefix="[RTGEN 206-500]" key="PREPROC_IO_COMP_CONFLICT_1950" tag="" content="Setting interface mode on port &apos;conv_bckwd/C&apos; to &apos;s_axilite &amp; ap_none&apos;." resolution=""/>
	<Message severity="INFO" prefix="[RTGEN 206-500]" key="PREPROC_IO_COMP_CONFLICT_1950" tag="" content="Setting interface mode on port &apos;conv_bckwd/H&apos; to &apos;s_axilite &amp; ap_none&apos;." resolution=""/>
	<Message severity="INFO" prefix="[RTGEN 206-500]" key="PREPROC_IO_COMP_CONFLICT_1950" tag="" content="Setting interface mode on port &apos;conv_bckwd/W_r&apos; to &apos;s_axilite &amp; ap_none&apos;." resolution=""/>
	<Message severity="INFO" prefix="[RTGEN 206-500]" key="PREPROC_IO_COMP_CONFLICT_1950" tag="" content="Setting interface mode on port &apos;conv_bckwd/FH&apos; to &apos;s_axilite &amp; ap_none&apos;." resolution=""/>
	<Message severity="INFO" prefix="[RTGEN 206-500]" key="PREPROC_IO_COMP_CONFLICT_1950" tag="" content="Setting interface mode on port &apos;conv_bckwd/FW&apos; to &apos;s_axilite &amp; ap_none&apos;." resolution=""/>
	<Message severity="INFO" prefix="[RTGEN 206-500]" key="PREPROC_IO_COMP_CONFLICT_1950" tag="" content="Setting interface mode on function &apos;conv_bckwd&apos; to &apos;s_axilite &amp; ap_ctrl_hs&apos;." resolution=""/>
	<Message severity="INFO" prefix="[RTGEN 206-100]" key="RTGEN_100_851" tag="" content="Bundling port &apos;x&apos;, &apos;w&apos;, &apos;dx&apos;, &apos;dw&apos;, &apos;db&apos;, &apos;dy&apos;, &apos;F&apos;, &apos;C&apos;, &apos;H&apos;, &apos;W_r&apos;, &apos;FH&apos;, &apos;FW&apos; to AXI-Lite port CTRL." resolution=""/>
	<Message severity="INFO" prefix="[RTGEN 206-100]" key="RTGEN_100_855" tag="" content="Generating core module &apos;am_addmul_11ns_10ns_8ns_17_4_1&apos;: 5 instance(s)." resolution=""/>
	<Message severity="INFO" prefix="[RTGEN 206-100]" key="RTGEN_100_855" tag="" content="Generating core module &apos;mac_muladd_14ns_8ns_17ns_17_4_1&apos;: 1 instance(s)." resolution=""/>
	<Message severity="INFO" prefix="[RTGEN 206-100]" key="RTGEN_100_855" tag="" content="Generating core module &apos;mac_muladd_16s_16s_23ns_23_4_1&apos;: 2 instance(s)." resolution=""/>
	<Message severity="INFO" prefix="[RTGEN 206-100]" key="RTGEN_100_855" tag="" content="Generating core module &apos;mac_muladd_7ns_8ns_10ns_14_4_1&apos;: 1 instance(s)." resolution=""/>
	<Message severity="INFO" prefix="[RTGEN 206-100]" key="RTGEN_100_855" tag="" content="Generating core module &apos;mul_31ns_32ns_63_2_1&apos;: 1 instance(s)." resolution=""/>
	<Message severity="INFO" prefix="[RTGEN 206-100]" key="RTGEN_100_855" tag="" content="Generating core module &apos;mul_31ns_64ns_95_5_1&apos;: 2 instance(s)." resolution=""/>
	<Message severity="INFO" prefix="[RTGEN 206-100]" key="RTGEN_100_855" tag="" content="Generating core module &apos;mul_31s_31s_31_2_1&apos;: 23 instance(s)." resolution=""/>
	<Message severity="INFO" prefix="[RTGEN 206-100]" key="RTGEN_100_855" tag="" content="Generating core module &apos;mul_32ns_32ns_64_2_1&apos;: 4 instance(s)." resolution=""/>
	<Message severity="INFO" prefix="[RTGEN 206-100]" key="RTGEN_100_855" tag="" content="Generating core module &apos;mul_32ns_64ns_96_5_1&apos;: 1 instance(s)." resolution=""/>
	<Message severity="INFO" prefix="[RTGEN 206-100]" key="RTGEN_100_855" tag="" content="Generating core module &apos;mul_4ns_8ns_11_1_1&apos;: 5 instance(s)." resolution=""/>
	<Message severity="INFO" prefix="[RTGEN 206-100]" key="RTGEN_100_856" tag="" content="Finished creating RTL model for &apos;conv_bckwd&apos;." resolution=""/>
	<Message severity="INFO" prefix="[HLS 200-111]" key="HLS_111_966" tag="RUNTIME" content="Finished Creating RTL model: CPU user time: 0.9 seconds. CPU system time: 0.03 seconds. Elapsed time: 0.93 seconds; current allocated memory: 210.173 MB." resolution=""/>
	<Message severity="INFO" prefix="[RTMG 210-282]" key="RTMG_282_1796" tag="" content="Generating pipelined core: &apos;conv_bckwd_mul_31s_31s_31_2_1_Multiplier_0&apos;" resolution=""/>
	<Message severity="INFO" prefix="[RTMG 210-282]" key="RTMG_282_1796" tag="" content="Generating pipelined core: &apos;conv_bckwd_mul_32ns_32ns_64_2_1_Multiplier_1&apos;" resolution=""/>
	<Message severity="INFO" prefix="[RTMG 210-282]" key="RTMG_282_1796" tag="" content="Generating pipelined core: &apos;conv_bckwd_mul_4ns_8ns_11_1_1_Multiplier_2&apos;" resolution=""/>
	<Message severity="INFO" prefix="[RTMG 210-282]" key="RTMG_282_1796" tag="" content="Generating pipelined core: &apos;conv_bckwd_mul_31ns_64ns_95_5_1_Multiplier_3&apos;" resolution=""/>
	<Message severity="INFO" prefix="[RTMG 210-282]" key="RTMG_282_1796" tag="" content="Generating pipelined core: &apos;conv_bckwd_mul_31ns_32ns_63_2_1_Multiplier_4&apos;" resolution=""/>
	<Message severity="INFO" prefix="[RTMG 210-282]" key="RTMG_282_1796" tag="" content="Generating pipelined core: &apos;conv_bckwd_mul_32ns_64ns_96_5_1_Multiplier_5&apos;" resolution=""/>
	<Message severity="INFO" prefix="[RTMG 210-278]" key="RTMG_278_1790" tag="" content="Implementing memory &apos;conv_bckwd_xbuf_V_ram (RAM)&apos; using auto RAMs." resolution=""/>
	<Message severity="INFO" prefix="[RTMG 210-278]" key="RTMG_278_1790" tag="" content="Implementing memory &apos;conv_bckwd_wbuf_V_ram (RAM)&apos; using auto RAMs." resolution=""/>
	<Message severity="INFO" prefix="[RTMG 210-278]" key="RTMG_278_1790" tag="" content="Implementing memory &apos;conv_bckwd_dxbuf_V_ram (RAM)&apos; using auto RAMs." resolution=""/>
	<Message severity="INFO" prefix="[RTMG 210-278]" key="RTMG_278_1790" tag="" content="Implementing memory &apos;conv_bckwd_dbbuf_V_ram (RAM)&apos; using auto RAMs." resolution=""/>
	<Message severity="INFO" prefix="[HLS 200-111]" key="HLS_111_966" tag="RUNTIME" content="Finished Generating all RTL models: CPU user time: 3.67 seconds. CPU system time: 0.06 seconds. Elapsed time: 3.73 seconds; current allocated memory: 231.244 MB." resolution=""/>
	<Message severity="INFO" prefix="[VHDL 208-304]" key="VHDL_304_1066" tag="" content="Generating VHDL RTL for conv_bckwd." resolution=""/>
	<Message severity="INFO" prefix="[VLOG 209-307]" key="VLOG_307_1067" tag="" content="Generating Verilog RTL for conv_bckwd." resolution=""/>
	<Message severity="INFO" prefix="[HLS 200-1603]" key="HLS 200-1603" tag="VITIS_INTERFACE" content="Design has MAXI bursts and missed bursts, see Vitis HLS GUI synthesis summary report for detailed information." resolution=""/>
	<Message severity="INFO" prefix="[HLS 200-790]" key="HLS 200-790" tag="LOOP,VITIS_KERNEL" content="**** Loop Constraint Status: All loop constraints were NOT satisfied." resolution=""/>
	<Message severity="INFO" prefix="[HLS 200-789]" key="HLS 200-789" tag="THROUGHPUT,VITIS_KERNEL" content="**** Estimated Fmax: 136.99 MHz" resolution=""/>
	<Message severity="INFO" prefix="[HLS 200-111]" key="HLS_111_966" tag="RUNTIME" content="Finished Command csynth_design CPU user time: 13.95 seconds. CPU system time: 0.53 seconds. Elapsed time: 13.86 seconds; current allocated memory: 231.910 MB." resolution=""/>
</Messages>
